photo_condenser/__init__.py
photo_condenser/__main__.py
photo_condenser/app_controller.py
photo_condenser/image_comparator.py
photo_condenser/image_data.py
photo_condenser/img_cache.py
photo_condenser/model.py
photo_condenser/ui/__init__.py
photo_condenser/ui/main_window.py
photo_condenser/ui/components/__init__.py
photo_condenser/ui/components/address_bar.py
photo_condenser/ui/components/image_viewer.py
photo_condenser/ui/components/status_bar.py
photo_condenser/ui/views/base_view.py
photo_condenser/ui/views/landscape_view.py
photo_condenser/ui/views/loading_view.py
photo_condenser/ui/views/portrait_view.py
photo_condenser-0.0.3.dist-info/licenses/LICENSE
photo_condenser-0.0.3.dist-info/WHEEL
photo_condenser-0.0.3.dist-info/METADATA
photo_condenser-0.0.3.dist-info/RECORD
