Metadata-Version: 2.4
Name: photo_condenser
Version: 0.0.3
Summary: Photo Deduplicator - A tool to find and remove duplicate or similar images.
Author-email: mova <mova@users.noreply.github.com>
Requires-Python: >=3.8
Classifier: Programming Language :: Python :: 3
Classifier: License :: OSI Approved :: MIT License
Classifier: Operating System :: OS Independent
License-File: LICENSE
Requires-Dist: Pillow>=9.0.0
Requires-Dist: numpy>=1.19.0
Requires-Dist: onnxruntime
Requires-Dist: pytest >=2.7.3 ; extra == "dev"
Requires-Dist: pytest-cov ; extra == "dev"
Requires-Dist: bump2version ; extra == "dev"
Requires-Dist: black ; extra == "dev"
Requires-Dist: pre-commit ; extra == "dev"
Requires-Dist: ruff ; extra == "dev"
Requires-Dist: mock ; extra == "dev"
Requires-Dist: pylint>=2.12.0 ; extra == "dev"
Requires-Dist: flit ; extra == "dev"
Requires-Dist: sphinx ; extra == "doc"
Requires-Dist: sphinx_rtd_theme ; extra == "doc"
Requires-Dist: autodocsumm ; extra == "doc"
Requires-Dist: readthedocs-sphinx-search ; extra == "doc"
Project-URL: Bug Tracker, https://github.com/mova/photo_condenser/issues
Project-URL: Homepage, https://github.com/mova/photo_condenser
Provides-Extra: dev
Provides-Extra: doc
